veda/pytorch/__init__.py
veda/pytorch/autocast.py
veda/pytorch/autoload.py
veda/pytorch/extension.py
veda/pytorch/nn_module.py
veda/pytorch/serialization.py
veda/pytorch/storage.py
veda/pytorch/tensor.py
veda/pytorch/ve.py
veda/pytorch/csrc/veda/pytorch/Allocator.cpp
veda/pytorch/csrc/veda/pytorch/Allocator.h
veda/pytorch/csrc/veda/pytorch/Guard.cpp
veda/pytorch/csrc/veda/pytorch/Guard.h
veda/pytorch/csrc/veda/pytorch/__ns.h
veda/pytorch/csrc/veda/pytorch/api.h
veda/pytorch/csrc/veda/pytorch/aten_registry.cpp
veda/pytorch/csrc/veda/pytorch/c10d/ProcessGroupVEDA.cpp
veda/pytorch/csrc/veda/pytorch/c10d/ProcessGroupVEDA.h
veda/pytorch/csrc/veda/pytorch/c10d/c10d_registry.cpp
veda/pytorch/csrc/veda/pytorch/c10d/veda_registry.cpp
veda/pytorch/csrc/veda/pytorch/dprint.cpp
veda/pytorch/csrc/veda/pytorch/dprint.h
veda/pytorch/csrc/veda/pytorch/fallback.cpp
veda/pytorch/csrc/veda/pytorch/op_arange.cpp
veda/pytorch/csrc/veda/pytorch/op_binary.cpp
veda/pytorch/csrc/veda/pytorch/op_bitwise.cpp
veda/pytorch/csrc/veda/pytorch/op_cat.cpp
veda/pytorch/csrc/veda/pytorch/op_complex.cpp
veda/pytorch/csrc/veda/pytorch/op_copy.cpp
veda/pytorch/csrc/veda/pytorch/op_cumsum.cpp
veda/pytorch/csrc/veda/pytorch/op_fill.cpp
veda/pytorch/csrc/veda/pytorch/op_masked_fill.cpp
veda/pytorch/csrc/veda/pytorch/op_masked_select.cpp
veda/pytorch/csrc/veda/pytorch/op_mean.cpp
veda/pytorch/csrc/veda/pytorch/op_norm.cpp
veda/pytorch/csrc/veda/pytorch/op_reduce.cpp
veda/pytorch/csrc/veda/pytorch/op_softmax.cpp
veda/pytorch/csrc/veda/pytorch/op_tensor.cpp
veda/pytorch/csrc/veda/pytorch/op_unary.cpp
veda/pytorch/csrc/veda/pytorch/op_where.cpp
veda_pytorch-14.0.1.dist-info/LICENSE
veda_pytorch-14.0.1.dist-info/METADATA
veda_pytorch-14.0.1.dist-info/top_list.txt
veda_pytorch-14.0.1.dist-info/WHEEL
veda_pytorch-14.0.1.dist-info/entry_points.txt
veda_pytorch-14.0.1.dist-info/RECORD
