Metadata-Version: 2.1
Name: veda-pytorch
Version: 14.0.1
Requires-Python: >=3.7
Summary: VEDA PyTorch
Author: Nicolas Weber
Author-email: nicolas.weber@neclab.eu
Classifier: License :: OSI Approved :: BSD License
Classifier: Programming Language :: Python :: 3 :: Only
Classifier: Programming Language :: C
Classifier: Programming Language :: C++
Download-URL: https://github.com/sx-aurora/veda-pytorch/tags
License: 3 BSD-License
Platform: linux_x86_x64
Requires-Dist: veda (>= 2.3.0, < 3)
Requires-Dist: tungl (>= 0.1.5, < 1)
Requires-Dist: veda-tensors (>= 0.1.9, < 2)
Requires-Dist: torch
Requires-Dist: ninja
Requires-Dist: packaging
